viggoportalcontador/__init__.py
viggoportalcontador/resources.py
viggoportalcontador/subsystem/__init__.py
viggoportalcontador/subsystem/controle/__init__.py
viggoportalcontador/subsystem/controle/configuracao_portal_contador/__init__.py
viggoportalcontador/subsystem/controle/configuracao_portal_contador/manager.py
viggoportalcontador/subsystem/controle/configuracao_portal_contador/resource.py
viggoportalcontador/subsystem/controle/configuracao_portal_contador/router.py
viggoportalcontador/subsystem/controle/portal_contador/__init__.py
viggoportalcontador/subsystem/controle/portal_contador/controller.py
viggoportalcontador/subsystem/controle/portal_contador/manager.py
viggoportalcontador/subsystem/controle/portal_contador/resource.py
viggoportalcontador/subsystem/controle/portal_contador/router.py
viggoportalcontador-1.0.0.dist-info/AUTHORS
viggoportalcontador-1.0.0.dist-info/METADATA
viggoportalcontador-1.0.0.dist-info/WHEEL
viggoportalcontador-1.0.0.dist-info/top_level.txt
viggoportalcontador-1.0.0.dist-info/RECORD
